deep_lyapunov/__init__.py
deep_lyapunov/analyzer.py
deep_lyapunov/config.py
deep_lyapunov/results.py
deep_lyapunov/metrics/__init__.py
deep_lyapunov/metrics/convergence.py
deep_lyapunov/metrics/dimensionality.py
deep_lyapunov/metrics/lyapunov.py
deep_lyapunov/tracking/__init__.py
deep_lyapunov/tracking/perturbation.py
deep_lyapunov/tracking/tracker.py
deep_lyapunov/visualization/__init__.py
deep_lyapunov/visualization/plots.py
deep_lyapunov-0.1.2.dist-info/licenses/LICENSE
deep_lyapunov-0.1.2.dist-info/METADATA
deep_lyapunov-0.1.2.dist-info/WHEEL
deep_lyapunov-0.1.2.dist-info/top_level.txt
deep_lyapunov-0.1.2.dist-info/RECORD
