Metadata-Version: 2.4
Name: deep-lyapunov
Version: 0.1.2
Summary: Analyze neural network training stability using Lyapunov exponents and perturbation-based trajectory analysis
Author-email: Rajesh Sampathkumar <rexplorations@gmail.com>
License: MIT
Project-URL: Homepage, https://github.com/aiexplorations/deep-lyapunov
Project-URL: Documentation, https://github.com/aiexplorations/deep-lyapunov#readme
Project-URL: Repository, https://github.com/aiexplorations/deep-lyapunov
Project-URL: Issues, https://github.com/aiexplorations/deep-lyapunov/issues
Keywords: deep-learning,neural-networks,training-dynamics,lyapunov-exponents,stability-analysis,pytorch,machine-learning
Classifier: Development Status :: 4 - Beta
Classifier: Intended Audience :: Developers
Classifier: Intended Audience :: Science/Research
Classifier: License :: OSI Approved :: MIT License
Classifier: Operating System :: OS Independent
Classifier: Programming Language :: Python :: 3
Classifier: Programming Language :: Python :: 3.9
Classifier: Programming Language :: Python :: 3.10
Classifier: Programming Language :: Python :: 3.11
Classifier: Programming Language :: Python :: 3.12
Classifier: Topic :: Scientific/Engineering :: Artificial Intelligence
Classifier: Topic :: Scientific/Engineering :: Mathematics
Requires-Python: >=3.9
License-File: LICENSE
Requires-Dist: torch>=2.0
Requires-Dist: numpy>=1.24
Requires-Dist: matplotlib>=3.7
Requires-Dist: scikit-learn>=1.0
Provides-Extra: full
Requires-Dist: seaborn>=0.12; extra == "full"
Requires-Dist: tqdm>=4.65; extra == "full"
Provides-Extra: dev
Requires-Dist: pytest>=7.0; extra == "dev"
Requires-Dist: pytest-cov>=4.0; extra == "dev"
Requires-Dist: black>=23.0; extra == "dev"
Requires-Dist: isort>=5.12; extra == "dev"
Requires-Dist: mypy>=1.0; extra == "dev"
Requires-Dist: ruff>=0.1; extra == "dev"
Provides-Extra: docs
Requires-Dist: mkdocs>=1.5; extra == "docs"
Requires-Dist: mkdocs-material>=9.0; extra == "docs"
Requires-Dist: mkdocstrings[python]>=0.24; extra == "docs"
Provides-Extra: all
Requires-Dist: deep-lyapunov[dev,docs,full]; extra == "all"
Dynamic: license-file
